jaw_tracking_system-1.1.0.dist-info/licenses/LICENSE
jts/__init__.py
jts/calibration_controllers.py
jts/core.py
jts/helper.py
jts/plotly_visualization.py
jts/precision_analysis.py
jts/qualisys.py
jts/qualisys_streaming.py
jts/streaming.py
jaw_tracking_system-1.1.0.dist-info/METADATA
jaw_tracking_system-1.1.0.dist-info/WHEEL
jaw_tracking_system-1.1.0.dist-info/entry_points.txt
jaw_tracking_system-1.1.0.dist-info/top_level.txt
jaw_tracking_system-1.1.0.dist-info/RECORD
