Metadata-Version: 2.4
Name: jaw-tracking-system
Version: 1.1.0
Summary: Modular and flexible jaw motion analysis framework (motion capture, calibration, registration, and analysis)
Home-page: https://github.com/paulotto/jaw_tracking_system
Download-URL: https://github.com/paulotto/jaw_tracking_system/tarball/1.1.0
Author: Paul-Otto Müller
Author-email: pmueller@sim.tu-darmstadt.de
License: CC BY-NC-SA 4.0
Project-URL: Source, https://github.com/paulotto/jaw_tracking_system
Project-URL: Bug Tracker, https://github.com/paulotto/jaw_tracking_system/issues
Project-URL: License, https://creativecommons.org/licenses/by-nc-sa/4.0/
Keywords: motion-capture jaw-analysis jaw-tracking biomechanics calibration registration
Classifier: Programming Language :: Python :: 3
Classifier: License :: Other/Proprietary License
Classifier: Operating System :: OS Independent
Classifier: Intended Audience :: Science/Research
Classifier: Topic :: Scientific/Engineering :: Information Analysis
Classifier: Topic :: Scientific/Engineering :: Visualization
Requires-Python: >=3.10
License-File: LICENSE
Requires-Dist: h5py
Requires-Dist: numpy
Requires-Dist: scipy
Requires-Dist: pandas
Requires-Dist: scikit-learn
Requires-Dist: matplotlib
Dynamic: author
Dynamic: author-email
Dynamic: classifier
Dynamic: description
Dynamic: description-content-type
Dynamic: download-url
Dynamic: home-page
Dynamic: keywords
Dynamic: license
Dynamic: license-file
Dynamic: project-url
Dynamic: requires-dist
Dynamic: requires-python
Dynamic: summary
